{"card_title":"Mestre de 2","card_type":"Creature","card_text":"Coleta: Você pode destruir uma criatura com 2 de poder.","traits":"Demônio","amber":0,"power":"4","armor":"0","rarity":"Variant","flavor_text":"O segundo pecado é a apatia.","card_number":"090","expansion":341,"is_maverick":false,"is_anomaly":false,"houses":[{"id":"00134873-14fe-4a4b-8635-017ac3fcd835","house":"Dis","normal":"https://mastervault-storage-prod.s3.amazonaws.com/media/card_front/pt/341_090_6PRCRMHM5G4W_pt.png","zoom":"https://cards-keyforge.s3.eu-north-1.amazonaws.com/media/pt/cota/Dis-090.png"}],"rules":[]}
