{"card_title":"Oficial de Operações Yshi","card_type":"Creature","card_text":"Provocar. \rCada vizinho do Oficial de Operações Yshi ganha “Luta/Coleta: Capture 1A.”","traits":"Espírito","amber":0,"power":"4","armor":"2","rarity":"Rare","flavor_text":"","card_number":"334","expansion":452,"is_maverick":false,"is_anomaly":false,"houses":[{"id":"29802126-e317-474c-a1b1-7d864fe8b484","house":"Star Alliance","normal":"https://cdn.keyforgegame.com/media/card_front/pt/452_334_7G8MRJWVF6JW_pt.png","zoom":"https://cards-keyforge.s3.eu-north-1.amazonaws.com/media/pt/wc/StarAlliance-334.png"}],"rules":[]}