{"id":"0e5b6e7b-f1f6-4968-b1fa-dbe2e0beccc6","card_title":"Cofre de Æmbar Sombrio","house":"Star Alliance","card_type":"Artifact","front_image":"https://cdn.keyforgegame.com/media/card_front/pt/479_001_457WQ26H976Q_pt.png","card_text":"Após você jogar uma criatura Mutante, compre uma carta.\r\nCada criatura Mutante amiga tem +2 de poder.","traits":"Lugar","amber":0,"power":null,"armor":null,"rarity":"Special","flavor_text":"O cofre se abriu e tudo mudou.","card_number":"001","expansion":479,"is_maverick":false,"is_anomaly":false,"is_enhanced":false}