{"id":"d977f197-6c5a-4f00-88dc-11be7eccacbc","card_title":"Lupo-Ladina","house":"Shadows","card_type":"Creature","front_image":"https://cdn.keyforgegame.com/media/card_front/pt/479_298_X76VJ5FW8PJ7_pt.png","card_text":"Elusivo. (A cada turno, na primeira vez que esta criatura for atacada, ela não causa nem recebe dano.)\rCombativo. (Quando usar esta criatura para lutar, ela não sofre dano da criatura atacada)","traits":"Mutante • Ladrão","amber":0,"power":"3","armor":null,"rarity":"Variant","flavor_text":"","card_number":"298","expansion":479,"is_maverick":false,"is_anomaly":false,"is_enhanced":false}