{"card_title":"Besta das Lendas Sombrias","card_type":"Action","card_text":"(T) Jogar: Keyraken ganha 1A para cada\nchave sua não forjada. Se a maré estiver\nalta, Keyraken arquiva 1 carta de aventura.","traits":null,"amber":0,"power":null,"armor":null,"rarity":"Rare","flavor_text":"”Há muito tempo, ele foi enclausurado além da\nnossa realidade. Quando retornar, nossa ascensão\nretomará seu curso.“ – Sacerdote Sombrio Anikava","card_number":"014","expansion":1001,"is_maverick":false,"is_anomaly":false,"is_enhanced":false,"is_non_deck":false,"houses":[{"id":"014","house":"Keyraken","normal":"https://cards-keyforge.s3.eu-north-1.amazonaws.com/media/pt/rotk/014.png","zoom":"https://cards-keyforge.s3.eu-north-1.amazonaws.com/media/pt/rotk/Keyraken-014.png"}],"rules":[]}