{"id":"0364d658-629b-46a6-8200-0f3de3d8d212","card_title":"Lança-Chamas","house":"Brobnar","card_type":"Artifact","front_image":"https://mastervault-storage-prod.s3.amazonaws.com/media/card_front/pt/452_018_X75WGJV5G8J2_pt.png","card_text":"Ação: Cause 1D a uma criatura, \rcom 1D de espalhar.","traits":"Arma","amber":0,"power":null,"armor":null,"rarity":"Uncommon","flavor_text":"Os bardos realmente estavam abrasando naquela noite.","card_number":"018","expansion":452,"is_maverick":false,"is_anomaly":false}
