{"id":"fdb9de9d-7c28-40c3-a590-140b1c79a374","card_title":"Corrente Sutil","house":"Shadows","card_type":"Action","front_image":"https://mastervault-storage-prod.s3.amazonaws.com/media/card_front/pt/452_262_7WG8C8P4FXGR_pt.png","card_text":"Jogar: O seu oponente descarta uma carta aleatória da própria mão.","traits":"","amber":1,"power":null,"armor":null,"rarity":"Uncommon","flavor_text":"A corrente nos mantém unidos, \rcorrendo pelas sombras.","card_number":"262","expansion":452,"is_maverick":false,"is_anomaly":false}
