{"card_title":"Verdades Desvendadas","card_type":"Action","card_text":"Jogar: Coloque um marcador de ignorância \nem cada uma de suas criaturas que não \nestejam no flanco. Enquanto uma criatura \ntiver um marcador de ignorância, a caixa de \ntexto dela é considerada em branco (exceto \npor atributos).","traits":null,"amber":1,"power":null,"armor":null,"rarity":"Uncommon","flavor_text":"A nossa vinda foi profetizada há eras.\" \n– Gêmeo do Mal de Dr. Escotera","card_number":"030_1","expansion":1002,"is_maverick":false,"is_anomaly":false,"is_enhanced":false,"is_non_deck":false,"houses":[{"id":"030","house":"Conspiracy","normal":"https://cards-keyforge.s3.eu-north-1.amazonaws.com/media/pt/tac/030.png","zoom":"https://cards-keyforge.s3.eu-north-1.amazonaws.com/media/pt/tac/Conspiracy-030.png"},{"id":"031","house":"Conspiracy","normal":"https://cards-keyforge.s3.eu-north-1.amazonaws.com/media/pt/tac/031.png","zoom":"https://cards-keyforge.s3.eu-north-1.amazonaws.com/media/pt/tac/Conspiracy-031.png"}],"rules":[]}