{"card_title":"Gruen Difuso (GM)","card_type":"Creature","card_text":"Presa – a criatura menos poderosa.\nLuta: A Conspiração ganha 1A.","traits":"Fera","amber":0,"power":"5","armor":null,"rarity":"Evil Twin","flavor_text":"\"6 braços = 300% de Poder de Abraço.\" \n– Dr. Escotera","card_number":"045_7","expansion":1002,"is_maverick":false,"is_anomaly":false,"is_enhanced":false,"is_non_deck":false,"houses":[{"id":"045","house":"Conspiracy","normal":"https://cards-keyforge.s3.eu-north-1.amazonaws.com/media/pt/tac/045.png","zoom":"https://cards-keyforge.s3.eu-north-1.amazonaws.com/media/pt/tac/Conspiracy-045.png"},{"id":"046","house":"Conspiracy","normal":"https://cards-keyforge.s3.eu-north-1.amazonaws.com/media/pt/tac/046.png","zoom":"https://cards-keyforge.s3.eu-north-1.amazonaws.com/media/pt/tac/Conspiracy-046.png"},{"id":"047","house":"Conspiracy","normal":"https://cards-keyforge.s3.eu-north-1.amazonaws.com/media/pt/tac/047.png","zoom":"https://cards-keyforge.s3.eu-north-1.amazonaws.com/media/pt/tac/Conspiracy-047.png"}],"rules":[]}