{"id":"220067ab-7ca2-4eda-b4df-dbf5f3eaeef7","card_title":"Clariel Forjaluz","house":"Sanctum","card_type":"Creature","front_image":"https://mastervault-storage-prod.s3.amazonaws.com/media/card_front/pt/496_067_QQX4XF7P5J9Q_pt.png","card_text":"Action: Switch a creature's power and armor for the remainder of the turn.","traits":"Angel","amber":0,"power":"5","armor":null,"rarity":"Evil Twin","flavor_text":"“Be very afraid.”","card_number":"067","expansion":496,"is_maverick":false,"is_anomaly":false,"is_enhanced":false,"is_non_deck":false}
