{"id":"247dc975-14bd-4bf2-89cd-8525d8d6762e","card_title":"O Protetor do Cofre","house":"Sanctum","card_type":"Creature","front_image":"https://cdn.keyforgegame.com/media/card_front/pt/496_091_GRHXCM2HH6W2_pt.png","card_text":"Your  cannot be stolen.","traits":"Spirit • Knight","amber":0,"power":"4","armor":"1","rarity":"Rare","flavor_text":"Few but the Archons possess the ability to<softreturn>detect the Vaults. Few but the Sanctum would<softreturn>presume to dictate which Archons are worthy.","card_number":"091","expansion":496,"is_maverick":false,"is_anomaly":false,"is_enhanced":false,"is_non_deck":false}