{"id":"74483b72-bd42-45cd-9bd1-1fa3bb05c9c7","card_title":"Capitão Kresage","house":"Logos","card_type":"Creature","front_image":"https://cdn.keyforgegame.com/media/card_front/en/496_003_QVQ44WVPJ2RW_en.png","card_text":"Each creature loses elusive, taunt, poison, and skirmish.","traits":"Cyborg","amber":0,"power":"6","armor":null,"rarity":"Evil Twin","flavor_text":"“I told you to stay off the furniture!”","card_number":"003","expansion":496,"is_maverick":false,"is_anomaly":false,"is_enhanced":false,"is_non_deck":false}
