{"id":"9815981a-0e61-4886-9036-de249c2307ce","card_title":"Ritual de Equilíbrio","house":"Untamed","card_type":"Artifact","front_image":"https://cdn.keyforgegame.com/media/card_front/pt/496_409_CCCJH6Q4C2GR_pt.png","card_text":"Action: If your opponent has 6 or more, steal 1.","traits":"Power","amber":0,"power":null,"armor":null,"rarity":"Uncommon","flavor_text":"Is balance a means to an end, or an end in itself? ","card_number":"409","expansion":496,"is_maverick":false,"is_anomaly":false,"is_enhanced":false,"is_non_deck":false}