{"id":"c3e06fb0-b6b9-493b-a5bb-6227b655349e","card_title":"Eng. de Foguetes Tryska","house":"Star Alliance","card_type":"Creature","front_image":"https://cdn.keyforgegame.com/media/card_front/en/496_300_56PWPH7564P_en.png","card_text":"(M) While the tide is high, Rocketeer Tryska’s neighbors enter play ready.","traits":"Human","amber":0,"power":"4","armor":null,"rarity":"Common","flavor_text":"“We’ll be together forever, Glub-Glub!”","card_number":"300","expansion":496,"is_maverick":false,"is_anomaly":false,"is_enhanced":false,"is_non_deck":false}
