{"card_title":"Mentorazilda","card_type":"Creature","card_text":"Elusivo. \rNo final do seu turno, coloque um marcador de trama em Mentorazilda. \rAção: Remova todos os marcadores de trama de Mentorazilda. Roube 1A para cada marcador de trama removido desta forma.","traits":"Elfo • Ladrão","amber":0,"power":"2","armor":null,"rarity":"Rare","flavor_text":"","card_number":"285","expansion":479,"is_maverick":false,"is_anomaly":false,"is_enhanced":false,"houses":[{"id":"5465462f-85f3-4f5e-b4fb-d76f9fc2ab9c","house":"Shadows","normal":"https://cdn.keyforgegame.com/media/card_front/pt/479_285_W8XG76QHF56M_pt.png","zoom":"https://cards-keyforge.s3.eu-north-1.amazonaws.com/media/pt/mm/Shadows-285.png"}],"rules":[]}