{"card_title":"Catalisar","card_type":"Action","card_text":"Jogar: Crie uma criatura token. Se o seu oponente tiver mais A do que você, arquive Catalisar.","traits":"","amber":0,"power":null,"armor":null,"rarity":"Common","flavor_text":"Após vigília incessante, um recém-criado cavaleiro traja sua armadura pela primeira vez.","card_number":"218","expansion":600,"is_maverick":false,"is_anomaly":false,"is_enhanced":false,"is_non_deck":false,"houses":[{"id":"d899da7f-6711-4f6d-9298-f9a2732a802f","house":"Sanctum","normal":"https://mastervault-storage-prod.s3.amazonaws.com/media/card_front/pt/600_218_059c20341603_pt.png","zoom":"https://cards-keyforge.s3.eu-north-1.amazonaws.com/media/pt/woe/Sanctum-218.png"}],"rules":[]}
