{"id":"02265c70-0624-40b2-aa03-67aa788e8fa3","card_title":"Fragmento de Vida","house":"Untamed","card_type":"Artifact","front_image":"https://mastervault-storage-prod.s3.amazonaws.com/media/card_front/pt/435_366_W2955Q987526_pt.png","card_text":"Ação: Embaralhe no seu baralho uma carta da sua pilha de descartes para cada Fragmento amigo.","traits":"Item • Fragmento","amber":0,"power":null,"armor":null,"rarity":"Rare","flavor_text":"Forjado a partir do instinto.","card_number":"366","expansion":435,"is_maverick":false,"is_anomaly":false}
