{"id":"5d65f805-2c14-4f51-8f0e-5b6597b0babd","card_title":"Pesquisador do Z.Y.X.","house":"Logos","card_type":"Creature","front_image":"https://cdn.keyforgegame.com/media/card_front/pt/435_123_C3CH8VRX8J8G_pt.png","card_text":"Jogar: Arquive a carta do topo do seu baralho ou do topo da sua pilha de descartes.","traits":"Humano • Cientista","amber":0,"power":"2","armor":null,"rarity":"Common","flavor_text":"“Nós só nos preocupamos com ‘poder’; deixe \rque o Santuário se preocupe com ‘dever’.”","card_number":"123","expansion":435,"is_maverick":false,"is_anomaly":false}