{"id":"64d696b9-4a8e-45de-88d7-fffbbcfc495c","card_title":"Xanthyx Colhedor","house":"Mars","card_type":"Creature","front_image":"https://mastervault-storage-prod.s3.amazonaws.com/media/card_front/pt/600_165_843e2ca45c37_pt.png","card_text":"Xanthyx Colhedor não pode ser usado enquanto tiver um vizinho não Marte.\nApós a Coleta: Ganhe 1.","traits":"Fera","amber":0,"power":"3","armor":"0","rarity":"Common","flavor_text":"","card_number":"165","expansion":600,"is_maverick":false,"is_anomaly":false,"is_enhanced":false,"is_non_deck":false}