{"id":"856785ce-27b3-4eb2-b5fb-19d08ae96190","card_title":"Espartassauro","house":"Saurian","card_type":"Creature","front_image":"https://mastervault-storage-prod.s3.amazonaws.com/media/card_front/pt/600_251_23fff60f2b9c_pt.png","card_text":"Após uma criatura amiga ser destruída, destrua todas as criaturas não Dinossauro.\nApós a Luta: Ganhe 2.","traits":"Soldado • Dinossauro","amber":0,"power":"6","armor":"1","rarity":"Rare","flavor_text":"","card_number":"251","expansion":600,"is_maverick":false,"is_anomaly":false,"is_enhanced":false,"is_non_deck":false}