{"card_title":"Bolton Punhocerrado","card_type":"Creature","card_text":"Elusivo.(A cada turno, na primeira vez \rem que esta criatura for atacada, nenhum dano é sofrido.)\rCombate.(Quando usar esta criatura para \rlutar, ela não sofre dano da criatura oponente.)","traits":"Elfo • Ladrão","amber":0,"power":"3","armor":null,"rarity":"Common","flavor_text":"“Eu adoro a vida de faca nos dentes dessa cidade!”","card_number":"271","expansion":435,"is_maverick":false,"is_anomaly":false,"houses":[{"id":"0ea16612-1395-4f72-b95b-8760c8a68de7","house":"Shadows","normal":"https://mastervault-storage-prod.s3.amazonaws.com/media/card_front/pt/435_271_QV7VR5Q8W8FH_pt.png","zoom":"https://cards-keyforge.s3.eu-north-1.amazonaws.com/media/pt/aoa/Shadows-271.png"}],"rules":[]}
