{"card_title":"Recrutar Soldado","card_type":"Action","card_text":"Play: Take control of an enemy creature with A on it. While under your control, it belongs to house Saurian. (Instead of its original house.)","traits":null,"amber":1,"power":null,"armor":null,"rarity":"Rare","flavor_text":null,"card_number":"138","expansion":496,"is_maverick":false,"is_anomaly":false,"is_enhanced":false,"is_non_deck":false,"houses":[{"id":"6df6944e-3dd0-4601-a9dc-a35191277e9b","house":"Saurian","normal":"https://cdn.keyforgegame.com/media/card_front/pt/496_138_GFM7J4PM6V46_pt.png","zoom":"https://cards-keyforge.s3.eu-north-1.amazonaws.com/media/pt/dt/Saurian-138.png"}],"rules":[]}